CodeComb_Core/__init__.py
CodeComb_Core/app.py
CodeComb_Core/codecomb.py
CodeComb_Core/config_shell.py
CodeComb_Core/embeddings.py
CodeComb_Core/env.py
CodeComb_Core/make_code_corpus.py
CodeComb_Core/query.py
CodeComb_Core/shell.py
CodeComb_Core/utils.py
CodeComb-0.1.9.dist-info/LICENSE
CodeComb-0.1.9.dist-info/METADATA
CodeComb-0.1.9.dist-info/WHEEL
CodeComb-0.1.9.dist-info/entry_points.txt
CodeComb-0.1.9.dist-info/top_level.txt
CodeComb-0.1.9.dist-info/RECORD
